cliwiper/__init__.py
cliwiper/cliwiper.py
cliwiper-1.1.4.dist-info/METADATA
cliwiper-1.1.4.dist-info/WHEEL
cliwiper-1.1.4.dist-info/licenses/LICENSE
cliwiper-1.1.4.dist-info/RECORD
