Metadata-Version: 2.1
Name: cliwiper
Version: 1.1.4
Summary: clear the cli
Project-URL: Homepage, https://github.com/SirX7/cliwiper
Project-URL: Bug Tracker, https://github.com/SirX7/cliwiper/issues
Author-email: Shall Mcfield <xhall.mc@protonmail.com>
License-Expression: MIT
License-File: LICENSE
Classifier: Development Status :: 5 - Production/Stable
Classifier: Intended Audience :: Information Technology
Classifier: License :: OSI Approved :: MIT License
Classifier: Operating System :: OS Independent
Classifier: Programming Language :: Python
Classifier: Programming Language :: Python :: 3
Classifier: Topic :: Internet
Requires-Python: >=3.8
